flock_sdk/__init__.py
flock_sdk/flock_model.py
flock_sdk/flock_sdk.py
flock_sdk-0.0.3.dist-info/METADATA
flock_sdk-0.0.3.dist-info/WHEEL
flock_sdk-0.0.3.dist-info/top_level.txt
flock_sdk-0.0.3.dist-info/RECORD
