Metadata-Version: 2.1
Name: flock-sdk
Version: 0.0.3
Summary: An SDK for building applications on top of FLock V1
Home-page: https://github.com/FLock-io/v1-sdk
Author: FLock.io
Author-email: info@flock.io
Keywords: blockchain,federated learning
Classifier: Programming Language :: Python :: 3
Classifier: Programming Language :: Python :: 3.7
Classifier: Programming Language :: Python :: 3.8
Classifier: Programming Language :: Python :: 3.9
Classifier: Programming Language :: Python :: 3.10
Classifier: License :: OSI Approved :: GNU General Public License v3 (GPLv3)
Classifier: Operating System :: OS Independent
Requires-Python: >=3.7
Requires-Dist: flask (==2.3.2)
Requires-Dist: loguru (==0.7.0)
